<?xml version="1.0"?>
<!DOCTYPE hibernate-mapping PUBLIC "-//Hibernate/Hibernate Mapping DTD 3.0//EN"
"http://hibernate.sourceforge.net/hibernate-mapping-3.0.dtd">
<!-- Generated 2012-5-7 10:42:55 by Hibernate Tools 3.4.0.CR1 -->
<hibernate-mapping>
    <class name="com.whan.hibernate.usermanage.AdmGroup" table="adm_group" catalog="usermanage">
        <id name="groupId" type="string">
            <column name="group_id" length="10" />
            <generator class="assigned" />
        </id>
        <property name="groupName" type="string">
            <column name="group_name" length="30" unique="true">
                <comment>&#215;&#233;&#195;&#251;&#215;&#214;</comment>
            </column>
        </property>
        <property name="aliasName" type="string">
            <column name="alias_name" length="30">
                <comment>&#215;&#233;&#177;&#240;&#195;&#251;</comment>
            </column>
        </property>
        <set name="admGroupRoles" table="adm_group_role" inverse="true" lazy="true" fetch="select">
            <key>
                <column name="group_id" length="10" not-null="true">
                    <comment>&#189;&#199;&#201;&#171;&#195;&#251;</comment>
                </column>
            </key>
            <one-to-many class="com.whan.hibernate.usermanage.AdmGroupRole" />
        </set>
        <set name="admUserGroups" table="adm_user_group" inverse="true" lazy="true" fetch="select">
            <key>
                <column name="group_id" length="10" not-null="true">
                    <comment>&#215;&#233;ID</comment>
                </column>
            </key>
            <one-to-many class="com.whan.hibernate.usermanage.AdmUserGroup" />
        </set>
    </class>
</hibernate-mapping>
